autonogame/__init__.py
autonogame/auth.py
autonogame/bot.py
autonogame/config.py
autonogame/crypto.py
autonogame/gui.py
autonogame/tab_account.py
autonogame/version.py
autonogame-1.2.0a0.dist-info/LICENSE
autonogame-1.2.0a0.dist-info/METADATA
autonogame-1.2.0a0.dist-info/WHEEL
autonogame-1.2.0a0.dist-info/entry_points.txt
autonogame-1.2.0a0.dist-info/top_level.txt
autonogame-1.2.0a0.dist-info/RECORD
