Metadata-Version: 2.1
Name: autonogame
Version: 1.2.0a0
Summary: Ogame bot
Home-page: https://github.com/tassoneroberto/autonogame
Author: Roberto Tassone
Author-email: roberto.tassone@proton.me
License: MIT
Keywords: ogame,bot,hack,script
Classifier: Development Status :: 2 - Pre-Alpha
Classifier: Intended Audience :: Developers
Classifier: Natural Language :: English
Classifier: Operating System :: Microsoft :: Windows
Classifier: Topic :: Software Development :: Build Tools
Classifier: Topic :: Software Development :: Libraries
Classifier: License :: OSI Approved :: MIT License
Classifier: Programming Language :: Python :: 3.10
License-File: LICENSE
Requires-Dist: cryptography (==37.0.2)
Requires-Dist: ogame (==8.4.0.22)
